revng/__init__.py
revng/py.typed
revng/model/__init__.py
revng/model/_generated.py
revng/model/external.py
revng/model/metaaddress.py
revng/model/mixins.py
revng/model/migrations/__init__.py
revng/model/migrations/versions/v2.py
revng/model/migrations/versions/v3.py
revng/model/migrations/versions/v4.py
revng/model/migrations/versions/v5.py
revng/model/migrations/versions/v6.py
revng/model/migrations/versions/v7.py
revng/pipeline_description/__init__.py
revng/pipeline_description/_generated.py
revng/project/__init__.py
revng/project/cli_project.py
revng/project/daemon_project.py
revng/project/local_daemon_project.py
revng/project/project.py
revng/ptml/__init__.py
revng/ptml/actions.py
revng/ptml/parser.py
revng/ptml/printer.py
revng/support/__init__.py
revng/support/artifacts.py
revng/support/location.py
revng/tupletree/__init__.py
revng-0.1.1763132671.dist-info/METADATA
revng-0.1.1763132671.dist-info/WHEEL
revng-0.1.1763132671.dist-info/top_level.txt
revng-0.1.1763132671.dist-info/RECORD
