Metadata-Version: 2.4
Name: revng
Version: 0.1.1763132671
Summary: Redistributable revng python package
Requires-Python: >=3.6
Requires-Dist: PyYAML<7.0,>=6.0.1
Requires-Dist: yachalk<1.0,>=0.1.7
Requires-Dist: llvmcpy<1.0,>=0.2.1
Requires-Dist: gql[aiohttp]<4.0,>=3.5.3
Requires-Dist: aiohttp<4.0,>=3.12.11
Requires-Dist: zstandard<1.0,>=0.23.0
Requires-Dist: pycparser<3.0,>=2.22
